[
  {
    "id": "RqfFauPXJx0",
    "urls":
    {
     "small": "https://github.com/GulayAdgzl/ColyakAPI/blob/main/w.jpg",
    },
  },
  {
    "id": "mYizSrdJkkU",
      "urls":
    {
     "small": "https://github.com/GulayAdgzl/ColyakAPI/blob/main/w.jpg",
    },
  
  },
  {
    "id": "c_Fvm6BW4Wg",
      "urls":
    {
     "small": "https://github.com/GulayAdgzl/ColyakAPI/blob/main/w.jpg",
    },
   
  },
  {
    "id": "oubKxRyYYQA",
       "urls":
    {
     "small": "https://github.com/GulayAdgzl/ColyakAPI/blob/main/w.jpg",
    },
   
  },
 
]
